sercher.py
sercher-1.0.1.dist-info/licenses/LICENSE
sercher-1.0.1.dist-info/METADATA
sercher-1.0.1.dist-info/WHEEL
sercher-1.0.1.dist-info/entry_points.txt
sercher-1.0.1.dist-info/top_level.txt
sercher-1.0.1.dist-info/RECORD
