Metadata-Version: 2.4
Name: sercher
Version: 1.0.1
Summary: GrokでWeb検索を実行するコマンドラインツール
Home-page: https://github.com/sugarkwork/sercher
Author: Sugar Knight
Author-email: Sugar Knight <your.email@example.com>
License: MIT
Project-URL: Homepage, https://github.com/sugarkwork/sercher
Project-URL: Repository, https://github.com/sugarkwork/sercher
Project-URL: Issues, https://github.com/sugarkwork/sercher/issues
Keywords: search,web,grok,ai,cli
Classifier: Development Status :: 4 - Beta
Classifier: Intended Audience :: Developers
Classifier: License :: OSI Approved :: MIT License
Classifier: Operating System :: OS Independent
Classifier: Programming Language :: Python :: 3
Classifier: Programming Language :: Python :: 3.6
Classifier: Programming Language :: Python :: 3.7
Classifier: Programming Language :: Python :: 3.8
Classifier: Programming Language :: Python :: 3.9
Classifier: Programming Language :: Python :: 3.10
Classifier: Programming Language :: Python :: 3.11
Classifier: Programming Language :: Python :: 3.12
Classifier: Topic :: Internet :: WWW/HTTP :: Indexing/Search
Classifier: Topic :: Utilities
Requires-Python: >=3.6
License-File: LICENSE
Requires-Dist: requests>=2.25.0
Requires-Dist: python-dotenv>=0.19.0
Dynamic: author
Dynamic: home-page
Dynamic: license-file
Dynamic: requires-python
